llama_index/readers/microsoft_outlook_emails/__init__.py
llama_index/readers/microsoft_outlook_emails/base.py
llama_index_readers_microsoft_outlook_emails-0.2.1.dist-info/METADATA
llama_index_readers_microsoft_outlook_emails-0.2.1.dist-info/WHEEL
llama_index_readers_microsoft_outlook_emails-0.2.1.dist-info/licenses/LICENSE
llama_index_readers_microsoft_outlook_emails-0.2.1.dist-info/RECORD
