Metadata-Version: 2.4
Name: llama-index-readers-microsoft-outlook-emails
Version: 0.2.1
Summary: llama-index readers microsoft_outlook_emails integration
Author-email: Your Name <you@example.com>
Maintainer: llama-index
License-Expression: MIT
License-File: LICENSE
Keywords: emails,microsoft 365,microsoft365,outlook
Requires-Python: <4.0,>=3.9
Requires-Dist: llama-index-core<0.15,>=0.13.0
